fennel/__init__.py
fennel/__main__.py
fennel/config.py
fennel/definition_generator.py
fennel/em_cascades.py
fennel/fennel.py
fennel/hadron_cascades.py
fennel/particle.py
fennel/photons.py
fennel/tracks.py
fennel/data/aachen.pkl
fennel/data/aachen_muon_production.pkl
fennel_seed-1.3.4.dist-info/LICENSE.txt
fennel_seed-1.3.4.dist-info/METADATA
fennel_seed-1.3.4.dist-info/WHEEL
fennel_seed-1.3.4.dist-info/top_level.txt
fennel_seed-1.3.4.dist-info/RECORD
