Metadata-Version: 2.1
Name: fennel-seed
Version: 1.3.4
Summary: Light-yields for tracks, and cascades
Home-page: https://github.com/MeighenBergerS/fennel
Author: Stephan Meighen-Berger
Author-email: stephan.meighenberger@gmail.com
License: MIT
License-File: LICENSE.txt
Requires-Dist: PyYAML
Requires-Dist: numpy
Requires-Dist: scipy
Requires-Dist: pandas
Provides-Extra: cpu
Requires-Dist: jax[cpu] ; extra == 'cpu'
Provides-Extra: interactive
Requires-Dist: nbstripout ; extra == 'interactive'
Requires-Dist: matplotlib ; extra == 'interactive'
Requires-Dist: jupyter ; extra == 'interactive'
Requires-Dist: tqdm ; extra == 'interactive'
Provides-Extra: jax
Requires-Dist: jax ; extra == 'jax'
Requires-Dist: jaxlib ; extra == 'jax'
